bashdown/__init__.py
bashdown-0.5.0.dist-info/LICENSE
bashdown-0.5.0.dist-info/METADATA
bashdown-0.5.0.dist-info/WHEEL
bashdown-0.5.0.dist-info/entry_points.txt
bashdown-0.5.0.dist-info/RECORD
