Metadata-Version: 2.1
Name: bashdown
Version: 0.5.0
Summary: Executes in-line bash in markdown files
Home-page: https://blog.sellorm.com/projects
License: MIT
Author: Mark Sellors
Author-email: github@5vcc.com
Requires-Python: >=3.8,<4.0
Classifier: License :: OSI Approved :: MIT License
Classifier: Programming Language :: Python :: 3
Classifier: Programming Language :: Python :: 3.8
Classifier: Programming Language :: Python :: 3.9
Classifier: Programming Language :: Python :: 3.10
Classifier: Programming Language :: Python :: 3.11
Project-URL: Repository, https://github.com/sellorm/bashdown
